[
  {
    "id": "DXB",
    "name": "Dubai",
    "country": "United Arab Emirates",
    "code": "DXB",
    "currency": "AED",
    "countryCode": "AE",
    "dialCode": "+971"
  },
  {
    "id": "LHR",
    "name": "London",
    "country": "United Kingdom",
    "code": "LHR",
    "currency": "GBP",
    "countryCode": "GB",
    "dialCode": "+44"
  },
  {
    "id": "JFK",
    "name": "New York",
    "country": "United States",
    "code": "JFK",
    "currency": "USD",
    "countryCode": "US",
    "dialCode": "+1"
  },
  {
    "id": "HND",
    "name": "Tokyo",
    "country": "Japan",
    "code": "HND",
    "currency": "JPY",
    "countryCode": "JP",
    "dialCode": "+81"
  },
  {
    "id": "CDG",
    "name": "Paris",
    "country": "France",
    "code": "CDG",
    "currency": "EUR",
    "countryCode": "FR",
    "dialCode": "+33"
  },
  {
    "id": "IST",
    "name": "Istanbul",
    "country": "Turkey",
    "code": "IST",
    "currency": "TRY",
    "countryCode": "TR",
    "dialCode": "+90"
  },
  {
    "id": "SIN",
    "name": "Singapore",
    "country": "Singapore",
    "code": "SIN",
    "currency": "SGD",
    "countryCode": "SG",
    "dialCode": "+65"
  },
  {
    "id": "AMS",
    "name": "Amsterdam",
    "country": "Netherlands",
    "code": "AMS",
    "currency": "EUR",
    "countryCode": "NL",
    "dialCode": "+31"
  },
  {
    "id": "ICN",
    "name": "Seoul",
    "country": "South Korea",
    "code": "ICN",
    "currency": "KRW",
    "countryCode": "KR",
    "dialCode": "+82"
  },
  {
    "id": "FRA",
    "name": "Frankfurt",
    "country": "Germany",
    "code": "FRA",
    "currency": "EUR",
    "countryCode": "DE",
    "dialCode": "+49"
  },
  {
    "id": "MAD",
    "name": "Madrid",
    "country": "Spain",
    "code": "MAD",
    "currency": "EUR",
    "countryCode": "ES",
    "dialCode": "+34"
  },
  {
    "id": "BCN",
    "name": "Barcelona",
    "country": "Spain",
    "code": "BCN",
    "currency": "EUR",
    "countryCode": "ES",
    "dialCode": "+34"
  },
  {
    "id": "DOH",
    "name": "Doha",
    "country": "Qatar",
    "code": "DOH",
    "currency": "QAR",
    "countryCode": "QA",
    "dialCode": "+974"
  },
  {
    "id": "BKK",
    "name": "Bangkok",
    "country": "Thailand",
    "code": "BKK",
    "currency": "THB",
    "countryCode": "TH",
    "dialCode": "+66"
  },
  {
    "id": "SFO",
    "name": "San Francisco",
    "country": "United States",
    "code": "SFO",
    "currency": "USD",
    "countryCode": "US",
    "dialCode": "+1"
  },
  {
    "id": "LAX",
    "name": "Los Angeles",
    "country": "United States",
    "code": "LAX",
    "currency": "USD",
    "countryCode": "US",
    "dialCode": "+1"
  },
  {
    "id": "ORD",
    "name": "Chicago",
    "country": "United States",
    "code": "ORD",
    "currency": "USD",
    "countryCode": "US",
    "dialCode": "+1"
  },
  {
    "id": "ATL",
    "name": "Atlanta",
    "country": "United States",
    "code": "ATL",
    "currency": "USD",
    "countryCode": "US",
    "dialCode": "+1"
  },
  {
    "id": "YYZ",
    "name": "Toronto",
    "country": "Canada",
    "code": "YYZ",
    "currency": "CAD",
    "countryCode": "CA",
    "dialCode": "+1"
  },
  {
    "id": "SYD",
    "name": "Sydney",
    "country": "Australia",
    "code": "SYD",
    "currency": "AUD",
    "countryCode": "AU",
    "dialCode": "+61"
  },
  {
    "id": "MEL",
    "name": "Melbourne",
    "country": "Australia",
    "code": "MEL",
    "currency": "AUD",
    "countryCode": "AU",
    "dialCode": "+61"
  },
  {
    "id": "BOM",
    "name": "Mumbai",
    "country": "India",
    "code": "BOM",
    "currency": "INR",
    "countryCode": "IN",
    "dialCode": "+91"
  },
  {
    "id": "DEL",
    "name": "Delhi",
    "country": "India",
    "code": "DEL",
    "currency": "INR",
    "countryCode": "IN",
    "dialCode": "+91"
  },
  {
    "id": "BLR",
    "name": "Bangalore",
    "country": "India",
    "code": "BLR",
    "currency": "INR",
    "countryCode": "IN",
    "dialCode": "+91"
  },
  {
    "id": "MAA",
    "name": "Chennai",
    "country": "India",
    "code": "MAA",
    "currency": "INR",
    "countryCode": "IN",
    "dialCode": "+91"
  },
  {
    "id": "HYD",
    "name": "Hyderabad",
    "country": "India",
    "code": "HYD",
    "currency": "INR",
    "countryCode": "IN",
    "dialCode": "+91"
  },
  {
    "id": "COK",
    "name": "Kochi",
    "country": "India",
    "code": "COK",
    "currency": "INR",
    "countryCode": "IN",
    "dialCode": "+91"
  },
  {
    "id": "CCJ",
    "name": "Kozhikode",
    "country": "India",
    "code": "CCJ",
    "currency": "INR",
    "countryCode": "IN",
    "dialCode": "+91"
  },
  {
    "id": "TRV",
    "name": "Thiruvananthapuram",
    "country": "India",
    "code": "TRV",
    "currency": "INR",
    "countryCode": "IN",
    "dialCode": "+91"
  },
  {
    "id": "HKG",
    "name": "Hong Kong",
    "country": "Hong Kong",
    "code": "HKG",
    "currency": "HKD",
    "countryCode": "HK",
    "dialCode": "+852"
  },
  {
    "id": "KUL",
    "name": "Kuala Lumpur",
    "country": "Malaysia",
    "code": "KUL",
    "currency": "MYR",
    "countryCode": "MY",
    "dialCode": "+60"
  },
  {
    "id": "CGK",
    "name": "Jakarta",
    "country": "Indonesia",
    "code": "CGK",
    "currency": "IDR",
    "countryCode": "ID",
    "dialCode": "+62"
  },
  {
    "id": "PEK",
    "name": "Beijing",
    "country": "China",
    "code": "PEK",
    "currency": "CNY",
    "countryCode": "CN",
    "dialCode": "+86"
  },
  {
    "id": "PVG",
    "name": "Shanghai",
    "country": "China",
    "code": "PVG",
    "currency": "CNY",
    "countryCode": "CN",
    "dialCode": "+86"
  },
  {
    "id": "CAN",
    "name": "Guangzhou",
    "country": "China",
    "code": "CAN",
    "currency": "CNY",
    "countryCode": "CN",
    "dialCode": "+86"
  },
  {
    "id": "JNB",
    "name": "Johannesburg",
    "country": "South Africa",
    "code": "JNB",
    "currency": "ZAR",
    "countryCode": "ZA",
    "dialCode": "+27"
  },
  {
    "id": "CAI",
    "name": "Cairo",
    "country": "Egypt",
    "code": "CAI",
    "currency": "EGP",
    "countryCode": "EG",
    "dialCode": "+20"
  },
  {
    "id": "ADD",
    "name": "Addis Ababa",
    "country": "Ethiopia",
    "code": "ADD",
    "currency": "ETB",
    "countryCode": "ET",
    "dialCode": "+251"
  },
  {
    "id": "LOS",
    "name": "Lagos",
    "country": "Nigeria",
    "code": "LOS",
    "currency": "NGN",
    "countryCode": "NG",
    "dialCode": "+234"
  },
  {
    "id": "GRU",
    "name": "São Paulo",
    "country": "Brazil",
    "code": "GRU",
    "currency": "BRL",
    "countryCode": "BR",
    "dialCode": "+55"
  },
  {
    "id": "BOG",
    "name": "Bogotá",
    "country": "Colombia",
    "code": "BOG",
    "currency": "COP",
    "countryCode": "CO",
    "dialCode": "+57"
  },
  {
    "id": "LIM",
    "name": "Lima",
    "country": "Peru",
    "code": "LIM",
    "currency": "PEN",
    "countryCode": "PE",
    "dialCode": "+51"
  },
  {
    "id": "MEX",
    "name": "Mexico City",
    "country": "Mexico",
    "code": "MEX",
    "currency": "MXN",
    "countryCode": "MX",
    "dialCode": "+52"
  },
  {
    "id": "MUC",
    "name": "Munich",
    "country": "Germany",
    "code": "MUC",
    "currency": "EUR",
    "countryCode": "DE",
    "dialCode": "+49"
  },
  {
    "id": "ZRH",
    "name": "Zurich",
    "country": "Switzerland",
    "code": "ZRH",
    "currency": "CHF",
    "countryCode": "CH",
    "dialCode": "+41"
  },
  {
    "id": "FCO",
    "name": "Rome",
    "country": "Italy",
    "code": "FCO",
    "currency": "EUR",
    "countryCode": "IT",
    "dialCode": "+39"
  },
  {
    "id": "MXP",
    "name": "Milan",
    "country": "Italy",
    "code": "MXP",
    "currency": "EUR",
    "countryCode": "IT",
    "dialCode": "+39"
  },
  {
    "id": "VIE",
    "name": "Vienna",
    "country": "Austria",
    "code": "VIE",
    "currency": "EUR",
    "countryCode": "AT",
    "dialCode": "+43"
  },
  {
    "id": "CPH",
    "name": "Copenhagen",
    "country": "Denmark",
    "code": "CPH",
    "currency": "DKK",
    "countryCode": "DK",
    "dialCode": "+45"
  },
  {
    "id": "ARN",
    "name": "Stockholm",
    "country": "Sweden",
    "code": "ARN",
    "currency": "SEK",
    "countryCode": "SE",
    "dialCode": "+46"
  },
  {
    "id": "OSL",
    "name": "Oslo",
    "country": "Norway",
    "code": "OSL",
    "currency": "NOK",
    "countryCode": "NO",
    "dialCode": "+47"
  },
  {
    "id": "HEL",
    "name": "Helsinki",
    "country": "Finland",
    "code": "HEL",
    "currency": "EUR",
    "countryCode": "FI",
    "dialCode": "+358"
  },
  {
    "id": "SVO",
    "name": "Moscow",
    "country": "Russia",
    "code": "SVO",
    "currency": "RUB",
    "countryCode": "RU",
    "dialCode": "+7"
  },
  {
    "id": "RUH",
    "name": "Riyadh",
    "country": "Saudi Arabia",
    "code": "RUH",
    "currency": "SAR",
    "countryCode": "SA",
    "dialCode": "+966"
  },
  {
    "id": "JED",
    "name": "Jeddah",
    "country": "Saudi Arabia",
    "code": "JED",
    "currency": "SAR",
    "countryCode": "SA",
    "dialCode": "+966"
  },
  {
    "id": "DMM",
    "name": "Dammam",
    "country": "Saudi Arabia",
    "code": "DMM",
    "currency": "SAR",
    "countryCode": "SA",
    "dialCode": "+966"
  },
  {
    "id": "MED",
    "name": "Medina",
    "country": "Saudi Arabia",
    "code": "MED",
    "currency": "SAR",
    "countryCode": "SA",
    "dialCode": "+966"
  },
  {
    "id": "KWI",
    "name": "Kuwait City",
    "country": "Kuwait",
    "code": "KWI",
    "currency": "KWD",
    "countryCode": "KW",
    "dialCode": "+965"
  },
  {
    "id": "BAH",
    "name": "Manama",
    "country": "Bahrain",
    "code": "BAH",
    "currency": "BHD",
    "countryCode": "BH",
    "dialCode": "+973"
  },
  {
    "id": "MCT",
    "name": "Muscat",
    "country": "Oman",
    "code": "MCT",
    "currency": "OMR",
    "countryCode": "OM",
    "dialCode": "+968"
  },
  {
    "id": "AUH",
    "name": "Abu Dhabi",
    "country": "United Arab Emirates",
    "code": "AUH",
    "currency": "AED",
    "countryCode": "AE",
    "dialCode": "+971"
  },
  {
    "id": "SHJ",
    "name": "Sharjah",
    "country": "United Arab Emirates",
    "code": "SHJ",
    "currency": "AED",
    "countryCode": "AE",
    "dialCode": "+971"
  },
  {
    "id": "AMM",
    "name": "Amman",
    "country": "Jordan",
    "code": "AMM",
    "currency": "JOD",
    "countryCode": "JO",
    "dialCode": "+962"
  },
  {
    "id": "BEY",
    "name": "Beirut",
    "country": "Lebanon",
    "code": "BEY",
    "currency": "LBP",
    "countryCode": "LB",
    "dialCode": "+961"
  },
  {
    "id": "TLV",
    "name": "Tel Aviv",
    "country": "Israel",
    "code": "TLV",
    "currency": "ILS",
    "countryCode": "IL",
    "dialCode": "+972"
  },
  {
    "id": "THR",
    "name": "Tehran",
    "country": "Iran",
    "code": "THR",
    "currency": "IRR",
    "countryCode": "IR",
    "dialCode": "+98"
  },
  {
    "id": "KHI",
    "name": "Karachi",
    "country": "Pakistan",
    "code": "KHI",
    "currency": "PKR",
    "countryCode": "PK",
    "dialCode": "+92"
  },
  {
    "id": "LHE",
    "name": "Lahore",
    "country": "Pakistan",
    "code": "LHE",
    "currency": "PKR",
    "countryCode": "PK",
    "dialCode": "+92"
  },
  {
    "id": "ISB",
    "name": "Islamabad",
    "country": "Pakistan",
    "code": "ISB",
    "currency": "PKR",
    "countryCode": "PK",
    "dialCode": "+92"
  },
  {
    "id": "DAC",
    "name": "Dhaka",
    "country": "Bangladesh",
    "code": "DAC",
    "currency": "BDT",
    "countryCode": "BD",
    "dialCode": "+880"
  },
  {
    "id": "CMB",
    "name": "Colombo",
    "country": "Sri Lanka",
    "code": "CMB",
    "currency": "LKR",
    "countryCode": "LK",
    "dialCode": "+94"
  },
  {
    "id": "KTM",
    "name": "Kathmandu",
    "country": "Nepal",
    "code": "KTM",
    "currency": "NPR",
    "countryCode": "NP",
    "dialCode": "+977"
  },
  {
    "id": "MNL",
    "name": "Manila",
    "country": "Philippines",
    "code": "MNL",
    "currency": "PHP",
    "countryCode": "PH",
    "dialCode": "+63"
  },
  {
    "id": "SGN",
    "name": "Ho Chi Minh City",
    "country": "Vietnam",
    "code": "SGN",
    "currency": "VND",
    "countryCode": "VN",
    "dialCode": "+84"
  },
  {
    "id": "HAN",
    "name": "Hanoi",
    "country": "Vietnam",
    "code": "HAN",
    "currency": "VND",
    "countryCode": "VN",
    "dialCode": "+84"
  },
  {
    "id": "AKL",
    "name": "Auckland",
    "country": "New Zealand",
    "code": "AKL",
    "currency": "NZD",
    "countryCode": "NZ",
    "dialCode": "+64"
  },
  {
    "id": "MIA",
    "name": "Miami",
    "country": "United States",
    "code": "MIA",
    "currency": "USD",
    "countryCode": "US",
    "dialCode": "+1"
  },
  {
    "id": "DFW",
    "name": "Dallas",
    "country": "United States",
    "code": "DFW",
    "currency": "USD",
    "countryCode": "US",
    "dialCode": "+1"
  },
  {
    "id": "IAH",
    "name": "Houston",
    "country": "United States",
    "code": "IAH",
    "currency": "USD",
    "countryCode": "US",
    "dialCode": "+1"
  },
  {
    "id": "SEA",
    "name": "Seattle",
    "country": "United States",
    "code": "SEA",
    "currency": "USD",
    "countryCode": "US",
    "dialCode": "+1"
  },
  {
    "id": "YVR",
    "name": "Vancouver",
    "country": "Canada",
    "code": "YVR",
    "currency": "CAD",
    "countryCode": "CA",
    "dialCode": "+1"
  },
  {
    "id": "YUL",
    "name": "Montreal",
    "country": "Canada",
    "code": "YUL",
    "currency": "CAD",
    "countryCode": "CA",
    "dialCode": "+1"
  },
  {
    "id": "EZE",
    "name": "Buenos Aires",
    "country": "Argentina",
    "code": "EZE",
    "currency": "ARS",
    "countryCode": "AR",
    "dialCode": "+54"
  },
  {
    "id": "SCL",
    "name": "Santiago",
    "country": "Chile",
    "code": "SCL",
    "currency": "CLP",
    "countryCode": "CL",
    "dialCode": "+56"
  },
  {
    "id": "PTY",
    "name": "Panama City",
    "country": "Panama",
    "code": "PTY",
    "currency": "USD",
    "countryCode": "PA",
    "dialCode": "+507"
  },
  {
    "id": "NBO",
    "name": "Nairobi",
    "country": "Kenya",
    "code": "NBO",
    "currency": "KES",
    "countryCode": "KE",
    "dialCode": "+254"
  },
  {
    "id": "CMN",
    "name": "Casablanca",
    "country": "Morocco",
    "code": "CMN",
    "currency": "MAD",
    "countryCode": "MA",
    "dialCode": "+212"
  },
  {
    "id": "TUN",
    "name": "Tunis",
    "country": "Tunisia",
    "code": "TUN",
    "currency": "TND",
    "countryCode": "TN",
    "dialCode": "+216"
  },
  {
    "id": "ALG",
    "name": "Algiers",
    "country": "Algeria",
    "code": "ALG",
    "currency": "DZD",
    "countryCode": "DZ",
    "dialCode": "+213"
  },
  {
    "id": "DUB",
    "name": "Dublin",
    "country": "Ireland",
    "code": "DUB",
    "currency": "EUR",
    "countryCode": "IE",
    "dialCode": "+353"
  },
  {
    "id": "EDI",
    "name": "Edinburgh",
    "country": "United Kingdom",
    "code": "EDI",
    "currency": "GBP",
    "countryCode": "GB",
    "dialCode": "+44"
  },
  {
    "id": "MAN",
    "name": "Manchester",
    "country": "United Kingdom",
    "code": "MAN",
    "currency": "GBP",
    "countryCode": "GB",
    "dialCode": "+44"
  },
  {
    "id": "BRU",
    "name": "Brussels",
    "country": "Belgium",
    "code": "BRU",
    "currency": "EUR",
    "countryCode": "BE",
    "dialCode": "+32"
  },
  {
    "id": "GVA",
    "name": "Geneva",
    "country": "Switzerland",
    "code": "GVA",
    "currency": "CHF",
    "countryCode": "CH",
    "dialCode": "+41"
  },
  {
    "id": "LIS",
    "name": "Lisbon",
    "country": "Portugal",
    "code": "LIS",
    "currency": "EUR",
    "countryCode": "PT",
    "dialCode": "+351"
  },
  {
    "id": "ATH",
    "name": "Athens",
    "country": "Greece",
    "code": "ATH",
    "currency": "EUR",
    "countryCode": "GR",
    "dialCode": "+30"
  },
  {
    "id": "WAW",
    "name": "Warsaw",
    "country": "Poland",
    "code": "WAW",
    "currency": "PLN",
    "countryCode": "PL",
    "dialCode": "+48"
  },
  {
    "id": "PRG",
    "name": "Prague",
    "country": "Czech Republic",
    "code": "PRG",
    "currency": "CZK",
    "countryCode": "CZ",
    "dialCode": "+420"
  },
  {
    "id": "BUD",
    "name": "Budapest",
    "country": "Hungary",
    "code": "BUD",
    "currency": "HUF",
    "countryCode": "HU",
    "dialCode": "+36"
  }
]